{
  "@context": "https://schema.org",
  "@type": "BlogPosting",
  "@id": "https://withframes.com/tr/changelog/1-6-macos/",
  "url": "https://withframes.com/tr/changelog/1-6-macos/",
  "mainEntityOfPage": {
    "@type": "WebPage",
    "@id": "https://withframes.com/tr/changelog/1-6-macos/"
  },
  "headline": "Ölçüm Modu Meta Verisi ve Performans İyileştirmeleri",
  "description": "macOS için Frames artık kapsamlı EXIF verileri için ölçüm modu meta veri desteği ve daha hızlı, daha kararlı çalışma için performans iyileştirmeleri içeriyor.",
  "datePublished": "2025-10-01T10:00:00.000Z",
  "dateModified": "2025-11-08T09:52:14+00:00",
  "inLanguage": "tr",
  "keywords": "fotoğraf,notlar,analog,film,rulo,negatif,defter,exif,veri,makinesi,35mm,resim,tarama,filmfoto,120mm,uygulama,iOS,iPhone,Mac",
  "author": {"@id": "https://withframes.com/#vincent-tantardini"},
  "publisher": {
    "@id": "https://withframes.com/#organization"
  },
  "image": {
    "@type": "ImageObject",
    "url": "https://withframes.com/lib/img/tr/changelog/og-image/1-6-macos-og-image.jpg",
    "contentUrl": "https://withframes.com/lib/img/tr/changelog/og-image/1-6-macos-og-image.jpg",
    "dateCreated": "2025-10-01T10:00:00.000Z",
    "caption": "Eksiksiz EXIF verileri için ölçüm modu meta veri desteği gösteren Frames macOS uygulaması"
  }}