{
  "@context": "https://schema.org",
  "@type": "BlogPosting",
  "@id": "https://withframes.com/fr/changelog/1-12-ios/",
  "url": "https://withframes.com/fr/changelog/1-12-ios/",
  "headline": "Danois, finnois, norvégien, vietnamien et 4 langues supplémentaires",
  "name": "Danois, finnois, norvégien, vietnamien et 4 langues supplémentaires · Frames",
  "description": "Cette version majeure de localisation apporte Frames à encore plus de photographes argentiques dans le monde.",
  "datePublished": "2025-10-03T10:00:00.000Z",
  "dateModified": "2025-10-15T10:25:31+00:00",
  "inLanguage": "fr",
  "author": {"@id": "https://withframes.com/#vincent-tantardini"},
  "publisher": {
    "@id": "https://withframes.com/#organization"
  },
  "image": {
    "@type": "ImageObject",
    "url": "https://withframes.com/lib/img/shared/changelog/frames-1.12.0-1.png",
    "width": "400",
    "height": "300"
  }}