{
  "@context": "https://schema.org",
  "@type": "BlogPosting",
  "@id": "https://withframes.com/ru/changelog/1-14-ios/",
  "url": "https://withframes.com/ru/changelog/1-14-ios/",
  "mainEntityOfPage": {
    "@type": "WebPage",
    "@id": "https://withframes.com/ru/changelog/1-14-ios/"
  },
  "headline": "Обновлённый интерфейс с новым Liquid Glass Design от Apple",
  "description": "Frames использует современный язык дизайна Apple с полным обновлением интерфейса, вдохновлённым эстетикой Liquid Glass Design. От полностью переработанной панели записи...",
  "datePublished": "2025-10-30T10:00:00.000Z",
  "dateModified": "2025-11-07T14:09:56+00:00",
  "inLanguage": "ru",
  "author": {"@id": "https://withframes.com/#vincent-tantardini"},
  "publisher": {
    "@id": "https://withframes.com/#organization"
  },
  "image": {
    "@type": "ImageObject",
    "url": "https://withframes.com/lib/img/ru/changelog/og-image/1-14-ios-og-image.jpg",
    "contentUrl": "https://withframes.com/lib/img/ru/changelog/og-image/1-14-ios-og-image.jpg",
    "dateCreated": "2025-10-30T10:00:00.000Z",
    "caption": "Приложение для плёночной фотографии Frames с новым интерфейсом Liquid Design от Apple и переработанной панелью записи"
  }}