{
  "@context": "https://schema.org",
  "@type": "BlogPosting",
  "@id": "https://withframes.com/zh-hant/changelog/1-7-macos/",
  "url": "https://withframes.com/zh-hant/changelog/1-7-macos/",
  "headline": "新增丹麥語、芬蘭語、挪威語、越南語等 8 種語言支援",
  "name": "新增丹麥語、芬蘭語、挪威語、越南語等 8 種語言支援 · Frames",
  "description": "此次重大本地化更新將 Frames macOS 版帶給全球更多使用者,新增八種語言支援,同時最佳化所有現有語言的翻譯...",
  "datePublished": "2025-10-02T10:00:00.000Z",
  "dateModified": "2025-10-14T09:05:07+00:00",
  "inLanguage": "zh-hant",
  "author": {"@id": "https://withframes.com/#vincent-tantardini"},
  "publisher": {
    "@id": "https://withframes.com/#organization"
  },
  "image": {
    "@type": "ImageObject",
    "url": "https://withframes.com/lib/img/shared/changelog/frames-mac-1.7.0-1.png",
    "width": "400",
    "height": "300"
  }}