{
  "@context": "https://schema.org",
  "@type": "BreadcrumbList",
  "itemListElement": [
    {
      "@type": "ListItem",
      "position": 1,
      "name": "होम",
      "item": "https://withframes.com/hi/"
    },
    {
      "@type": "ListItem",
      "position": 2,
      "name": "ब्लॉग",
      "item": "https://withframes.com/hi/blog/"
    },
    {
      "@type": "ListItem",
      "position": 3,
      "name": "2026 में सर्वश्रेष्ठ नए फिल्म कैमरे: जो आप वाकई खरीद सकते हैं",
      "item": "https://withframes.com/hi/blog/2026-mein-kharidne-ke-liye-best-film-camera/"
    }  ]
}