{
  "@context": "https://schema.org",
  "@type": "BlogPosting",
  "@id": "https://withframes.com/hi/changelog/1-0-ios/",
  "url": "https://withframes.com/hi/changelog/1-0-ios/",
  "mainEntityOfPage": {
    "@type": "WebPage",
    "@id": "https://withframes.com/hi/changelog/1-0-ios/"
  },
  "headline": "Frames लॉन्च: आपकी एनालॉग फ़ोटोग्राफ़ी नोटबुक",
  "description": "iOS पर फ़िल्म फ़ोटोग्राफ़ी metadata को फ़ील्ड में ट्रैक करें और macOS के साथ स्कैन की गई छवियों में EXIF डेटा एम्बेड करें। 200+ फ़िल्म stocks के साथ संपूर्ण एनालॉग workflow।",
  "datePublished": "2025-04-01T03:02:00.000Z",
  "dateModified": "2025-11-08T09:52:06+00:00",
  "inLanguage": "hi",
  "keywords": "फोटोग्राफी,नोट्स,एनालॉग,फिल्म,रोल,नेगेटिव,नोटबुक,EXIF,मेटाडेटा,कैमरा,35mm,इमेज,स्कैन,फिल्मफोटो,शॉट,फोटो,ऐप,एप्लिकेशन,iOS,iPhone,Mac",
  "author": {"@id": "https://withframes.com/#vincent-tantardini"},
  "publisher": {
    "@id": "https://withframes.com/#organization"
  },
  "image": {
    "@type": "ImageObject",
    "url": "https://withframes.com/lib/img/hi/changelog/og-image/1-0-ios-og-image.jpg",
    "contentUrl": "https://withframes.com/lib/img/hi/changelog/og-image/1-0-ios-og-image.jpg",
    "dateCreated": "2025-04-01T03:02:00.000Z",
    "caption": "एनालॉग camera metadata और roll विवरण लॉग करने के लिए Frames फ़िल्म फ़ोटोग्राफ़ी ऐप इंटरफ़ेस"
  }}