{
  "@context": "https://schema.org",
  "@type": "BlogPosting",
  "@id": "https://withframes.com/ja/changelog/1-4-ios/",
  "url": "https://withframes.com/ja/changelog/1-4-ios/",
  "headline": "フィルター記録サポート",
  "name": "フィルター記録サポート · Frames",
  "description": "各フレームにUV、ND、CPL、その他のフィルターを記録。完全なEXIF埋め込みのためMacと同期する包括的なメタデータで完全なアナログ記録を実現。",
  "datePublished": "2025-08-20T10:00:00.000Z",
  "dateModified": "2025-10-15T11:56:55+00:00",
  "inLanguage": "ja",
  "author": {"@id": "https://withframes.com/#vincent-tantardini"},
  "publisher": {
    "@id": "https://withframes.com/#organization"
  },
  "image": {
    "@type": "ImageObject",
    "url": "https://withframes.com/lib/img/ja/changelog/frames-1.4.0-1.png",
    "width": "400",
    "height": "300"
  }}