{
  "@context": "https://schema.org",
  "@type": "BlogPosting",
  "@id": "https://withframes.com/it/changelog/1-5-ios/",
  "url": "https://withframes.com/it/changelog/1-5-ios/",
  "headline": "Nuove Pellicole, Sistema Apertura Ridisegnato e Cambio Obiettivo",
  "name": "Nuove Pellicole, Sistema Apertura Ridisegnato e Cambio Obiettivo · Frames",
  "description": "Questo aggiornamento espande la libreria di pellicole con nuove emulsioni, ridisegna completamente la gestione dell'apertura con sequenze f-stop...",
  "datePublished": "2025-09-03T10:00:00.000Z",
  "dateModified": "2025-10-14T10:13:26+00:00",
  "inLanguage": "it",
  "author": {"@id": "https://withframes.com/#vincent-tantardini"},
  "publisher": {
    "@id": "https://withframes.com/#organization"
  },
  "image": {
    "@type": "ImageObject",
    "url": "https://withframes.com/lib/img/it/changelog/frames-1.5.0-1.png",
    "width": "400",
    "height": "300"
  }}