{
  "@context": "https://schema.org",
  "@type": "BlogPosting",
  "@id": "https://withframes.com/sv/changelog/1-7-ios/",
  "url": "https://withframes.com/sv/changelog/1-7-ios/",
  "headline": "Fullt tillgänglighetsstöd och registreringsförbättringar",
  "name": "Fullt tillgänglighetsstöd och registreringsförbättringar · Frames",
  "description": "Komplett stöd för Apples tillgänglighetsfunktioner: Större text, Mörkt gränssnitt, Tillräcklig kontrast. Förbättrat arbetsflöde och automatisk ifyllning av bländarvärden.",
  "datePublished": "2025-09-10T10:00:00.000Z",
  "dateModified": "2025-10-15T14:00:30+00:00",
  "inLanguage": "sv",
  "author": {"@id": "https://withframes.com/#vincent-tantardini"},
  "publisher": {
    "@id": "https://withframes.com/#organization"
  },
  "image": {
    "@type": "ImageObject",
    "url": "https://withframes.com/lib/img/shared/changelog/frames-1.7.0-1.png",
    "width": "400",
    "height": "300"
  }}