{
  "@context": "https://schema.org",
  "@type": "BlogPosting",
  "@id": "https://withframes.com/vi/changelog/1-6-ios/",
  "url": "https://withframes.com/vi/changelog/1-6-ios/",
  "headline": "Chuỗi tốc độ màn trập tùy chỉnh & Cải thiện bản đồ",
  "description": "Đặt chuỗi tốc độ màn trập tùy chỉnh cho mỗi máy ảnh, chỉ hiển thị các tốc độ mà máy ảnh của bạn thực sự hỗ trợ.",
  "datePublished": "2025-09-05T10:00:00.000Z",
  "dateModified": "2025-10-21T18:13:17+00:00",
  "inLanguage": "vi",
  "author": {"@id": "https://withframes.com/#vincent-tantardini"},
  "publisher": {
    "@id": "https://withframes.com/#organization"
  },
  "image": {
    "@type": "ImageObject",
    "url": "https://withframes.com/lib/img/vi/changelog/frames-1.6.0-1.png",
    "width": "400",
    "height": "300"
  }}