{
  "@context": "https://schema.org",
  "@type": "BlogPosting",
  "@id": "https://withframes.com/th/changelog/1-8-ios/",
  "url": "https://withframes.com/th/changelog/1-8-ios/",
  "headline": "ส่งออกไฟล์ TXT สำหรับบันทึกฟิล์ม",
  "name": "ส่งออกไฟล์ TXT สำหรับบันทึกฟิล์ม · Frames",
  "description": "ผู้ใช้ Pro สามารถส่งออกบันทึกม้วนฟิล์มเป็นไฟล์ TXT ได้แล้ว เหมาะสำหรับพิมพ์บันทึกสนามหรือสร้างแผ่นอ้างอิงแบบรวดเร็วสำหรับงานห้องมืด",
  "datePublished": "2025-09-15T10:00:00.000Z",
  "dateModified": "2025-10-12T23:02:53+00:00",
  "inLanguage": "th",
  "author": {
    "@type": "Person",
    "name": "Vincent Tantardini"
  },
  "publisher": {
    "@id": "https://withframes.com/#organization"
  },
  "image": {
    "@type": "ImageObject",
    "url": "https://withframes.com/lib/img/shared/changelog/frames-1.8.0-1.png",
    "width": "400",
    "height": "300"
  }}