{
  "@context": "https://schema.org",
  "@type": "Blog",
  "@id": "https://withframes.com/el/blog/topic/exoplismos/",
  "url": "https://withframes.com/el/blog/topic/exoplismos/",
  "name": "Εξοπλισμός Φωτογραφίας Φιλμ | Frames Blog",
  "description": "Νέες κάμερες, φιλμ, φακοί και εξοπλισμός για αναλογικούς φωτογράφους. Κριτικές και οδηγοί αγοράς.",
  "inLanguage": "el",
  "keywords": "φωτογραφία,σημειώσεις,αναλογικό,φιλμ,ρολό,αρνητικό,σημειωματάριο,exif,μεταδεδομένα,κάμερα,εικόνα,35mm,εφαρμογή,iOS,iPhone,Mac",
  "publisher": {
    "@id": "https://withframes.com/#organization"
  },
  "blogPost": [
    {
      "@type": "BlogPosting",
      "@id": "https://withframes.com/el/blog/kaliteres-nees-kamberes-film-2026/",
      "url": "https://withframes.com/el/blog/kaliteres-nees-kamberes-film-2026/",
      "headline": "Οι Καλύτερες Νέες Κάμερες Φιλμ το 2026: Τι Μπορείτε Πραγματικά να Αγοράσετε",
      "description": "Ανακαλύψτε νέες κάμερες φιλμ διαθέσιμες το 2026. Από 35mm έως μεγάλο φορμά, από Pentax, Leica, Lomography και άλλες.",
      "datePublished": "2026-01-01T10:00:00.000Z",      "dateModified": "2026-01-01T10:00:00.000Z",      "inLanguage": "el",
      "keywords": "κάμερες φιλμ 2026, νέες κάμερες φιλμ, αγορά κάμερας φιλμ, κάμερα φιλμ 35mm, κάμερα μεσαίου φορμά, κάμερα μεγάλου φορμά, Pentax 17, Leica M6 επανέκδοση, Lomography MC-A, Analogue AF-1, φωτογραφία φιλμ 2026",
      "author": {"@id": "https://withframes.com/#vincent-tantardini"},
      "publisher": {
        "@id": "https://withframes.com/#organization"
      },
      "image": {
        "@type": "ImageObject",
        "url": "https://withframes.com/lib/img/el/changelog/og-image/kaliteres-nees-kamberes-film-2026-og-image.jpg",
        "contentUrl": "https://withframes.com/lib/img/el/changelog/og-image/kaliteres-nees-kamberes-film-2026-og-image.jpg",
        "dateCreated": "2026-01-01T10:00:00.000Z",
        "caption": "Κάμερα φωτογραφίας φιλμ Analog AF-1"
      }    }  ]
}