{
  "@context": "https://schema.org",
  "@type": "BlogPosting",
  "@id": "https://withframes.com/da/changelog/1-12-ios/",
  "url": "https://withframes.com/da/changelog/1-12-ios/",
  "headline": "Dansk, finsk, norsk, vietnamesisk og 4 flere sprog",
  "description": "Denne store lokaliseringsudgivelse bringer Frames til endnu flere filmfotografer verden over og tilføjer support til dansk, finsk, norsk, vietnamesisk,...",
  "datePublished": "2025-10-03T10:00:00.000Z",
  "dateModified": "2025-10-21T18:10:55+00:00",
  "inLanguage": "da",
  "author": {"@id": "https://withframes.com/#vincent-tantardini"},
  "publisher": {
    "@id": "https://withframes.com/#organization"
  },
  "image": {
    "@type": "ImageObject",
    "url": "https://withframes.com/lib/img/shared/changelog/frames-1.12.0-1.png",
    "width": "400",
    "height": "300"
  }}