{
  "@context": "https://schema.org",
  "@type": "BlogPosting",
  "@id": "https://withframes.com/vi/changelog/1-1-macos/",
  "url": "https://withframes.com/vi/changelog/1-1-macos/",
  "headline": "Hỗ trợ tệp TIFF",
  "name": "Hỗ trợ tệp TIFF · Frames",
  "description": "Nhập và xuất tệp TIFF với khả năng nhúng siêu dữ liệu đầy đủ. Hỗ trợ định dạng chuyên nghiệp cho ảnh scan chất lượng cao với quy trình tích hợp EXIF liền mạch.",
  "datePublished": "2025-06-27T10:00:00.000Z",
  "dateModified": "2025-10-18T09:25:44+00:00",
  "inLanguage": "vi",
  "author": {"@id": "https://withframes.com/#vincent-tantardini"},
  "publisher": {
    "@id": "https://withframes.com/#organization"
  },
  "image": {
    "@type": "ImageObject",
    "url": "https://withframes.com/lib/img/shared/changelog/frames-mac-1.1.0-1.png",
    "width": "400",
    "height": "300"
  }}