{
  "@context": "https://schema.org",
  "@type": "BlogPosting",
  "@id": "https://withframes.com/nl/changelog/1-12-ios/",
  "url": "https://withframes.com/nl/changelog/1-12-ios/",
  "headline": "Deens, Fins, Noors, Vietnamees en 4 andere talen",
  "name": "Deens, Fins, Noors, Vietnamees en 4 andere talen · Frames",
  "description": "Deze grote lokalisatie-release brengt Frames naar nog meer filmfotografen wereldwijd, met ondersteuning voor Deens, Fins, Noors, Vietnamees, Traditioneel...",
  "datePublished": "2025-10-03T10:00:00.000Z",
  "dateModified": "2025-10-14T11:15:28+00:00",
  "inLanguage": "nl",
  "author": {"@id": "https://withframes.com/#vincent-tantardini"},
  "publisher": {
    "@id": "https://withframes.com/#organization"
  },
  "image": {
    "@type": "ImageObject",
    "url": "https://withframes.com/lib/img/shared/changelog/frames-1.12.0-1.png",
    "width": "400",
    "height": "300"
  }}