{
  "@context": "https://schema.org",
  "@type": "BlogPosting",
  "@id": "https://withframes.com/uk/changelog/1-3-macos/",
  "url": "https://withframes.com/uk/changelog/1-3-macos/",
  "mainEntityOfPage": {
    "@type": "WebPage",
    "@id": "https://withframes.com/uk/changelog/1-3-macos/"
  },
  "headline": "Підтримка DNG Raw файлів",
  "description": "Вбудовуйте метадані у DNG raw файли поряд з форматами JPEG і TIFF. Повний робочий процес аналогової фотографії з вичерпними даними EXIF для професійної постобробки.",
  "datePublished": "2025-09-01T10:00:00.000Z",  "inLanguage": "uk",
  "keywords": "фотографія,нотатки,аналог,плівка,рол,негатив,нотатник,exif,метадані,камера,35mm,зображення,скан,120mm,фото,додаток,iOS,iPhone,Mac",
  "author": {"@id": "https://withframes.com/#vincent-tantardini"},
  "publisher": {
    "@id": "https://withframes.com/#organization"
  },
  "image": {
    "@type": "ImageObject",
    "url": "https://withframes.com/lib/img/uk/changelog/og-image/1-3-macos-og-image.jpg",
    "contentUrl": "https://withframes.com/lib/img/uk/changelog/og-image/1-3-macos-og-image.jpg",
    "dateCreated": "2025-09-01T10:00:00.000Z",
    "caption": "Додаток Frames для macOS з вбудовуванням метаданих DNG raw файлів для сканів аналогової фотографії"
  }}